README.md
setup.py
pyhanga/__init__.py
pyhanga/_session.py
pyhanga/commands.py
pyhanga/cost_template.py
pyhanga/create_stack.py
pyhanga/delete_stack.py
pyhanga/deploy_stack.py
pyhanga/describe_events.py
pyhanga/describe_resource.py
pyhanga/describe_stack.py
pyhanga/list_resources.py
pyhanga/list_stacks.py
pyhanga/protect_stack.py
pyhanga/pyhanga_constants.py
pyhanga/pyhanga_util.py
pyhanga/update_stack.py
pyhanga/upload_object.py
pyhanga.egg-info/PKG-INFO
pyhanga.egg-info/SOURCES.txt
pyhanga.egg-info/dependency_links.txt
pyhanga.egg-info/entry_points.txt
pyhanga.egg-info/requires.txt
pyhanga.egg-info/top_level.txt