Metadata-Version: 1.1
Name: pyhanga
Version: 0.90
Summary: Custom Python-based CloudFormation Command Line Interface
Home-page: https://github.com/boomary/pyhanga
Author: Sivadon Chaisiri
Author-email: javaboom@gmail.com
License: MIT
Download-URL: https://github.com/boomary/pyhanga/archive/v_90.tar.gz
Keywords: AWS,CloudFormation,CLI
Platform: UNKNOWN
Classifier: Development Status :: 4 - Beta
Classifier: Intended Audience :: Developers
Classifier: Topic :: Software Development :: Build Tools
Classifier: License :: OSI Approved :: MIT License
Classifier: Programming Language :: Python :: 3
